setup.py
fotatest/__init__.py
fotatest.egg-info/PKG-INFO
fotatest.egg-info/SOURCES.txt
fotatest.egg-info/dependency_links.txt
fotatest.egg-info/not-zip-safe
fotatest.egg-info/requires.txt
fotatest.egg-info/top_level.txt
fotatest/bin/fotatest