Metadata-Version: 1.0
Name: fotatest
Version: 0.03
Summary: UIE FOTA test app
Home-page: UNKNOWN
Author: Mike Cole
Author-email: UNKNOWN
License: Private
Platform: UNKNOWN
